{"properties": {"id": "58d92507268d1b091fd607dd", "length": 0.8136264699233987, "sensor": {"properties": {"manufacturer": "Volkswagen", "engineDisplacement": 1200, "fuelType": "gasoline", "model": "Golf Allstar", "constructionYear": 2016, "id": "57f7fdc2e4b01fb1bfdf272c"}, "type": "car"}}, "features": [{"properties": {"time": "2017-03-27T14:38:24Z", "phenomenons": {"GPS Speed": {"unit": "km/h", "value": 20.75894094703449}, "GPS Accuracy": {"unit": "%", "value": 6.0}, "Rpm": {"unit": "u/min", "value": 850.515104830265}, "Throttle Position": {"unit": "%", "value": 12.000000178813934}, "Engine Load": {"unit": "%", "value": 22.690571394791192}, "GPS VDOP": {"unit": "precision", "value": 0.7395551264286041}, "GPS HDOP": {"unit": "precision", "value": 0.8395551264286042}, "GPS Altitude": {"unit": "m", "value": 137.42502022408746}, "Intake Temperature": {"unit": "c", "value": 48.0}, "GPS PDOP": {"unit": "precision", "value": 1.1395551264286041}, "Consumption": {"unit": "l/h", "value": 0.8764582560409347}, "CO2": {"unit": "kg/h", "value": 2.059676901696197}, "Intake Pressure": {"unit": "kPa", "value": 34.0}, "GPS Bearing": {"unit": "deg", "value": 165.79911422585428}, "Calculated MAF": {"unit": "g/s", "value": 2.6662590530645267}, "Speed": {"unit": "km/h", "value": 21.00000062584877}}, "id": "58d92507268d1b091fd607df"}, "type": "Feature", "geometry": {"coordinates": [7.995810195531776, 52.343177228608226], "type": "Point"}}, {"properties": {"time": "2017-03-27T14:38:29Z", "phenomenons": {"GPS Speed": {"unit": "km/h", "value": 19.755517667158983}, "Calculated MAF": {"unit": "g/s", "value": 2.666865304632495}, "GPS Accuracy": {"unit": "%", "value": 6.000000178813934}, "Rpm": {"unit": "u/min", "value": 853.3574146032333}, "Throttle Position": {"unit": "%", "value": 11.999999910593033}, "Engine Load": {"unit": "%", "value": 22.459139131260258}, "GPS VDOP": {"unit": "precision", "value": 0.7999999761581422}, "GPS HDOP": {"unit": "precision", "value": 1.0365384310483932}, "Intake Temperature": {"unit": "c", "value": 49.000000547617674}, "GPS PDOP": {"unit": "precision", "value": 1.3365384221076966}, "Speed": {"unit": "km/h", "value": 19.0}, "Intake Pressure": {"unit": "kPa", "value": 34.00000101327896}, "CO2": {"unit": "kg/h", "value": 2.0601452291641245}, "GPS Bearing": {"unit": "deg", "value": 175.20654880894836}, "GPS Altitude": {"unit": "m", "value": 136.66471585039966}, "Consumption": {"unit": "l/h", "value": 0.8766575443251593}}, "id": "58d92507268d1b091fd607e1"}, "type": "Feature", "geometry": {"coordinates": [7.995809876598601, 52.342929154571124], "type": "Point"}}, {"properties": {"time": "2017-03-27T14:38:34Z", "phenomenons": {"GPS Speed": {"unit": "km/h", "value": 20.44313990092843}, "Intake Temperature": {"unit": "c", "value": 49.0}, "Rpm": {"unit": "u/min", "value": 849.0}, "Throttle Position": {"unit": "%", "value": 11.999999642372131}, "Engine Load": {"unit": "%", "value": 22.45591788803813}, "GPS VDOP": {"unit": "precision", "value": 0.9}, "GPS HDOP": {"unit": "precision", "value": 1.7}, "GPS Altitude": {"unit": "m", "value": 137.24266853760605}, "GPS Accuracy": {"unit": "%", "value": 7.999999761581421}, "GPS PDOP": {"unit": "precision", "value": 1.9}, "Speed": {"unit": "km/h", "value": 19.71043434739113}, "Intake Pressure": {"unit": "kPa", "value": 34.07989936321974}, "CO2": {"unit": "kg/h", "value": 2.0544422375506985}, "Calculated MAF": {"unit": "g/s", "value": 2.6594827617655405}, "GPS Bearing": {"unit": "deg", "value": 179.785036926281}, "Consumption": {"unit": "l/h", "value": 0.874230739383276}}, "id": "58d92507268d1b091fd607e2"}, "type": "Feature", "geometry": {"coordinates": [7.995823957727833, 52.34266902619134], "type": "Point"}}, {"properties": {"time": "2017-03-27T14:38:39Z", "phenomenons": {"GPS Speed": {"unit": "km/h", "value": 14.77157904767978}, "GPS Accuracy": {"unit": "%", "value": 8.0}, "Rpm": {"unit": "u/min", "value": 897.5044507980347}, "Throttle Position": {"unit": "%", "value": 13.000000387430191}, "Engine Load": {"unit": "%", "value": 28.084323263910164}, "GPS VDOP": {"unit": "precision", "value": 0.7558390349149704}, "GPS Bearing": {"unit": "deg", "value": 124.39461447505346}, "GPS HDOP": {"unit": "precision", "value": 0.8558390319347382}, "Intake Temperature": {"unit": "c", "value": 49.00000027380884}, "GPS PDOP": {"unit": "precision", "value": 1.1558390229940414}, "Speed": {"unit": "km/h", "value": 15.000000223517418}, "CO2": {"unit": "kg/h", "value": 2.607895954279811}, "Intake Pressure": {"unit": "kPa", "value": 40.922834634780884}, "Calculated MAF": {"unit": "g/s", "value": 3.375930560673209}, "GPS Altitude": {"unit": "m", "value": 138.51694444661766}, "Consumption": {"unit": "l/h", "value": 1.1097429592680046}}, "id": "58d92507268d1b091fd607e3"}, "type": "Feature", "geometry": {"coordinates": [7.995903966020267, 52.3424755486135], "type": "Point"}}, {"properties": {"time": "2017-03-27T14:38:44Z", "phenomenons": {"GPS Speed": {"unit": "km/h", "value": 17.732789902506624}, "GPS Accuracy": {"unit": "%", "value": 6.74674654006958}, "Rpm": {"unit": "u/min", "value": 1186.9319550991058}, "Throttle Position": {"unit": "%", "value": 13.0}, "Engine Load": {"unit": "%", "value": 15.456105783568404}, "GPS VDOP": {"unit": "precision", "value": 1.5417910456657409}, "GPS Bearing": {"unit": "deg", "value": 70.12796301837398}, "GPS HDOP": {"unit": "precision", "value": 1.0835820913314818}, "Intake Temperature": {"unit": "c", "value": 48.55018585920334}, "GPS PDOP": {"unit": "precision", "value": 1.883582091331482}, "Speed": {"unit": "km/h", "value": 18.0}, "Intake Pressure": {"unit": "kPa", "value": 33.00225912639871}, "CO2": {"unit": "kg/h", "value": 2.7852504778039533}, "Calculated MAF": {"unit": "g/s", "value": 3.605516620291961}, "GPS Altitude": {"unit": "m", "value": 139.33657257049717}, "Consumption": {"unit": "l/h", "value": 1.185212969278278}}, "id": "58d92507268d1b091fd607e4"}, "type": "Feature", "geometry": {"coordinates": [7.996186197582651, 52.34249665063072], "type": "Point"}}, {"properties": {"time": "2017-03-27T14:38:49Z", "phenomenons": {"GPS Speed": {"unit": "km/h", "value": 15.9329140186436}, "GPS Accuracy": {"unit": "%", "value": 8.0}, "Rpm": {"unit": "u/min", "value": 1128.6320776343346}, "Throttle Position": {"unit": "%", "value": 13.790172636508942}, "Engine Load": {"unit": "%", "value": 19.950786756663888}, "GPS VDOP": {"unit": "precision", "value": 0.8}, "GPS Bearing": {"unit": "deg", "value": 78.66895445456157}, "GPS HDOP": {"unit": "precision", "value": 1.0}, "Intake Temperature": {"unit": "c", "value": 48.99999963492155}, "GPS PDOP": {"unit": "precision", "value": 1.3}, "Speed": {"unit": "km/h", "value": 16.99999962002039}, "CO2": {"unit": "kg/h", "value": 3.0365631141797227}, "Intake Pressure": {"unit": "kPa", "value": 37.8915159702301}, "Calculated MAF": {"unit": "g/s", "value": 3.9308417192599565}, "GPS Altitude": {"unit": "m", "value": 139.38454432403}, "Consumption": {"unit": "l/h", "value": 1.2921545166722224}}, "id": "58d92507268d1b091fd607e5"}, "type": "Feature", "geometry": {"coordinates": [7.996541711132411, 52.342528022157694], "type": "Point"}}, {"properties": {"time": "2017-03-27T14:38:54Z", "phenomenons": {"GPS Speed": {"unit": "km/h", "value": 16.492218571672083}, "Calculated MAF": {"unit": "g/s", "value": 5.939630785422667}, "GPS Accuracy": {"unit": "%", "value": 6.0}, "Rpm": {"unit": "u/min", "value": 1138.807584643364}, "Throttle Position": {"unit": "%", "value": 15.000000335276127}, "Engine Load": {"unit": "%", "value": 29.33137759123585}, "GPS VDOP": {"unit": "precision", "value": 1.240663504600525}, "GPS HDOP": {"unit": "precision", "value": 1.0}, "Intake Temperature": {"unit": "c", "value": 49.0}, "GPS PDOP": {"unit": "precision", "value": 1.583886253833771}, "Consumption": {"unit": "l/h", "value": 1.9524878626235311}, "Intake Pressure": {"unit": "kPa", "value": 56.74373424053192}, "CO2": {"unit": "kg/h", "value": 4.588346477165298}, "GPS Altitude": {"unit": "m", "value": 139.41552005475728}, "GPS Bearing": {"unit": "deg", "value": 63.87874354441715}, "Speed": {"unit": "km/h", "value": 17.0}}, "id": "58d92507268d1b091fd607e6"}, "type": "Feature", "geometry": {"coordinates": [7.996829209969177, 52.34262791748872], "type": "Point"}}, {"properties": {"time": "2017-03-27T14:38:59Z", "phenomenons": {"GPS Speed": {"unit": "km/h", "value": 21.305493796872895}, "GPS Accuracy": {"unit": "%", "value": 6.000000178813934}, "Rpm": {"unit": "u/min", "value": 1432.2252952232957}, "Throttle Position": {"unit": "%", "value": 14.0}, "Engine Load": {"unit": "%", "value": 15.460975535815663}, "GPS VDOP": {"unit": "precision", "value": 1.0663690447807312}, "GPS HDOP": {"unit": "precision", "value": 0.9467261910438538}, "GPS Altitude": {"unit": "m", "value": 137.6544484052044}, "Intake Temperature": {"unit": "c", "value": 48.0}, "GPS PDOP": {"unit": "precision", "value": 1.4598214268684389}, "Speed": {"unit": "km/h", "value": 21.00000062584877}, "Intake Pressure": {"unit": "kPa", "value": 35.03695358335972}, "CO2": {"unit": "kg/h", "value": 3.5741751269914386}, "Calculated MAF": {"unit": "g/s", "value": 4.6267823762703}, "GPS Bearing": {"unit": "deg", "value": 69.63412932196684}, "Consumption": {"unit": "l/h", "value": 1.5209255859538036}}, "id": "58d92507268d1b091fd607e7"}, "type": "Feature", "geometry": {"coordinates": [7.997199507027997, 52.3426704917814], "type": "Point"}}, {"properties": {"time": "2017-03-27T14:39:04Z", "phenomenons": {"GPS Speed": {"unit": "km/h", "value": 21.783898589974115}, "Calculated MAF": {"unit": "g/s", "value": 6.105021632687608}, "GPS Accuracy": {"unit": "%", "value": 7.999999761581421}, "Rpm": {"unit": "u/min", "value": 1484.175732254982}, "Throttle Position": {"unit": "%", "value": 14.999999552965164}, "Engine Load": {"unit": "%", "value": 18.778237814562203}, "GPS VDOP": {"unit": "precision", "value": 1.5999999523162844}, "GPS HDOP": {"unit": "precision", "value": 1.1999999642372132}, "Intake Temperature": {"unit": "c", "value": 48.00000035762787}, "GPS PDOP": {"unit": "precision", "value": 1.9999999403953552}, "Speed": {"unit": "km/h", "value": 22.040446795523167}, "Intake Pressure": {"unit": "kPa", "value": 44.612903237342834}, "CO2": {"unit": "kg/h", "value": 4.7161103969809774}, "GPS Bearing": {"unit": "deg", "value": 79.50480222487863}, "GPS Altitude": {"unit": "m", "value": 136.15507251418745}, "Consumption": {"unit": "l/h", "value": 2.0068554880770115}}, "id": "58d92507268d1b091fd607e8"}, "type": "Feature", "geometry": {"coordinates": [7.997631786271936, 52.342688285232256], "type": "Point"}}, {"properties": {"time": "2017-03-27T14:39:09Z", "phenomenons": {"GPS Speed": {"unit": "km/h", "value": 6.050680355220152}, "Calculated MAF": {"unit": "g/s", "value": 2.6806641349895757}, "GPS Accuracy": {"unit": "%", "value": 6.0}, "Rpm": {"unit": "u/min", "value": 830.6784980297089}, "Throttle Position": {"unit": "%", "value": 12.000000089406967}, "Engine Load": {"unit": "%", "value": 23.485532953532243}, "GPS VDOP": {"unit": "precision", "value": 1.3}, "GPS HDOP": {"unit": "precision", "value": 0.9000000000000001}, "Intake Temperature": {"unit": "c", "value": 47.999998569488525}, "GPS PDOP": {"unit": "precision", "value": 1.6}, "Consumption": {"unit": "l/h", "value": 0.8811935247192141}, "Intake Pressure": {"unit": "kPa", "value": 34.99999947845936}, "CO2": {"unit": "kg/h", "value": 2.070804783090153}, "GPS Bearing": {"unit": "deg", "value": 80.015537596184}, "GPS Altitude": {"unit": "m", "value": 136.16677299300463}, "Speed": {"unit": "km/h", "value": 6.369426727294922}}, "id": "58d92507268d1b091fd607e9"}, "type": "Feature", "geometry": {"coordinates": [7.99800301608175, 52.34273623996717], "type": "Point"}}, {"properties": {"time": "2017-03-27T14:39:14Z", "phenomenons": {"GPS Speed": {"unit": "km/h", "value": 4.9646463999253285}, "Intake Temperature": {"unit": "c", "value": 47.99999928474426}, "Rpm": {"unit": "u/min", "value": 976.7184635400772}, "Throttle Position": {"unit": "%", "value": 13.0}, "Engine Load": {"unit": "%", "value": 26.848913877501673}, "GPS VDOP": {"unit": "precision", "value": 0.8588694214820862}, "GPS Bearing": {"unit": "deg", "value": 88.65192834545155}, "GPS HDOP": {"unit": "precision", "value": 0.9588694244623184}, "GPS Accuracy": {"unit": "%", "value": 5.999999821186066}, "GPS PDOP": {"unit": "precision", "value": 1.3177388310432434}, "Consumption": {"unit": "l/h", "value": 1.154527566205855}, "CO2": {"unit": "kg/h", "value": 2.7131397805837594}, "Intake Pressure": {"unit": "kPa", "value": 39.00000116229057}, "Calculated MAF": {"unit": "g/s", "value": 3.5121690670287276}, "GPS Altitude": {"unit": "m", "value": 136.220842273742}, "Speed": {"unit": "km/h", "value": 4.955106763169169}}, "id": "58d92507268d1b091fd607ea"}, "type": "Feature", "geometry": {"coordinates": [7.998097027809836, 52.34274239783534], "type": "Point"}}, {"properties": {"time": "2017-03-27T14:39:19Z", "phenomenons": {"GPS Speed": {"unit": "km/h", "value": 17.20429580243257}, "GPS Accuracy": {"unit": "%", "value": 6.0}, "Rpm": {"unit": "u/min", "value": 2048.8843450546265}, "Throttle Position": {"unit": "%", "value": 20.22416077554226}, "Engine Load": {"unit": "%", "value": 30.245098554976266}, "GPS VDOP": {"unit": "precision", "value": 1.3953140169382094}, "GPS HDOP": {"unit": "precision", "value": 0.9476570010185241}, "GPS Altitude": {"unit": "m", "value": 135.91705118754044}, "Intake Temperature": {"unit": "c", "value": 48.00000035762787}, "GPS PDOP": {"unit": "precision", "value": 1.6953140079975129}, "Speed": {"unit": "km/h", "value": 17.1054847240448}, "Intake Pressure": {"unit": "kPa", "value": 65.35334259271622}, "CO2": {"unit": "kg/h", "value": 9.537255105094927}, "GPS Bearing": {"unit": "deg", "value": 150.30859235810294}, "Calculated MAF": {"unit": "g/s", "value": 12.346010553598946}, "Consumption": {"unit": "l/h", "value": 4.0584064276999685}}, "id": "58d92507268d1b091fd607eb"}, "type": "Feature", "geometry": {"coordinates": [7.998204800287597, 52.34268541538883], "type": "Point"}}, {"properties": {"time": "2017-03-27T14:39:24Z", "phenomenons": {"GPS Speed": {"unit": "km/h", "value": 28.108468555703666}, "GPS Accuracy": {"unit": "%", "value": 8.0}, "Rpm": {"unit": "u/min", "value": 1935.9701784849167}, "Throttle Position": {"unit": "%", "value": 19.68639051914215}, "Engine Load": {"unit": "%", "value": 30.23052454234812}, "GPS VDOP": {"unit": "precision", "value": 1.0907331645488738}, "GPS Bearing": {"unit": "deg", "value": 166.00666852208815}, "GPS HDOP": {"unit": "precision", "value": 0.8999999731779099}, "Intake Temperature": {"unit": "c", "value": 48.000001430511475}, "GPS PDOP": {"unit": "precision", "value": 1.4325865149497985}, "Consumption": {"unit": "l/h", "value": 3.8999753087027726}, "CO2": {"unit": "kg/h", "value": 9.164941975451516}, "Intake Pressure": {"unit": "kPa", "value": 66.46498450264335}, "Calculated MAF": {"unit": "g/s", "value": 11.864049887016225}, "GPS Altitude": {"unit": "m", "value": 135.85315430807194}, "Speed": {"unit": "km/h", "value": 28.61855584383011}}, "id": "58d92507268d1b091fd607ec"}, "type": "Feature", "geometry": {"coordinates": [7.998310074491249, 52.3423992882895], "type": "Point"}}, {"properties": {"time": "2017-03-27T14:39:29Z", "phenomenons": {"GPS Speed": {"unit": "km/h", "value": 38.60912042221753}, "Intake Temperature": {"unit": "c", "value": 47.088589906692505}, "Rpm": {"unit": "u/min", "value": 1707.28624522686}, "Throttle Position": {"unit": "%", "value": 34.283222526311874}, "Engine Load": {"unit": "%", "value": 53.862189307095946}, "GPS VDOP": {"unit": "precision", "value": 0.800000023841858}, "GPS HDOP": {"unit": "precision", "value": 1.0000000298023224}, "GPS Altitude": {"unit": "m", "value": 137.58924849489608}, "GPS Accuracy": {"unit": "%", "value": 8.0}, "GPS PDOP": {"unit": "precision", "value": 1.300000038743019}, "Consumption": {"unit": "l/h", "value": 5.268045272677554}, "Intake Pressure": {"unit": "kPa", "value": 101.51696074008942}, "CO2": {"unit": "kg/h", "value": 12.379906390792252}, "Calculated MAF": {"unit": "g/s", "value": 16.025832723257842}, "GPS Bearing": {"unit": "deg", "value": 166.1248906575529}, "Speed": {"unit": "km/h", "value": 39.15533922612667}}, "id": "58d92507268d1b091fd607ed"}, "type": "Feature", "geometry": {"coordinates": [7.998475697632644, 52.34198390492523], "type": "Point"}}, {"properties": {"time": "2017-03-27T14:39:34Z", "phenomenons": {"GPS Speed": {"unit": "km/h", "value": 35.589072373932936}, "Calculated MAF": {"unit": "g/s", "value": 3.0942879399369074}, "GPS Accuracy": {"unit": "%", "value": 8.000000238418579}, "Rpm": {"unit": "u/min", "value": 939.4481384754181}, "Throttle Position": {"unit": "%", "value": 12.771929442882538}, "Engine Load": {"unit": "%", "value": 24.29199323142327}, "GPS VDOP": {"unit": "precision", "value": 0.9430814564228058}, "GPS HDOP": {"unit": "precision", "value": 0.8523061811923981}, "Intake Temperature": {"unit": "c", "value": 47.0}, "GPS PDOP": {"unit": "precision", "value": 1.2953876376152038}, "Speed": {"unit": "km/h", "value": 34.18498757481575}, "CO2": {"unit": "kg/h", "value": 2.3903278977186906}, "Intake Pressure": {"unit": "kPa", "value": 35.611650228500366}, "GPS Bearing": {"unit": "deg", "value": 165.9925889455526}, "GPS Altitude": {"unit": "m", "value": 138.93972323156032}, "Consumption": {"unit": "l/h", "value": 1.0171608075398684}}, "id": "58d92507268d1b091fd607ee"}, "type": "Feature", "geometry": {"coordinates": [7.998657347903216, 52.34150796669201], "type": "Point"}}, {"properties": {"time": "2017-03-27T14:39:39Z", "phenomenons": {"GPS Speed": {"unit": "km/h", "value": 18.875887553618554}, "Calculated MAF": {"unit": "g/s", "value": 9.632875043513918}, "GPS Accuracy": {"unit": "%", "value": 8.0}, "Rpm": {"unit": "u/min", "value": 1256.5202445983887}, "Throttle Position": {"unit": "%", "value": 19.00595235824585}, "Engine Load": {"unit": "%", "value": 36.72158816377009}, "GPS VDOP": {"unit": "precision", "value": 1.0362538039684295}, "GPS HDOP": {"unit": "precision", "value": 0.9000000268220902}, "Intake Temperature": {"unit": "c", "value": 48.000001430511475}, "GPS PDOP": {"unit": "precision", "value": 1.357502555847168}, "Speed": {"unit": "km/h", "value": 18.142196126282215}, "CO2": {"unit": "kg/h", "value": 7.441366284812834}, "Intake Pressure": {"unit": "kPa", "value": 83.14670500159264}, "GPS Altitude": {"unit": "m", "value": 139.10867294746822}, "GPS Bearing": {"unit": "deg", "value": 229.15381006906682}, "Consumption": {"unit": "l/h", "value": 3.166538844601206}}, "id": "58d92507268d1b091fd607ef"}, "type": "Feature", "geometry": {"coordinates": [7.998634561473897, 52.34127903670566], "type": "Point"}}, {"properties": {"time": "2017-03-27T14:39:44Z", "phenomenons": {"GPS Speed": {"unit": "km/h", "value": 25.54143704228727}, "Calculated MAF": {"unit": "g/s", "value": 4.722722949836002}, "Intake Temperature": {"unit": "c", "value": 47.0}, "Rpm": {"unit": "u/min", "value": 1739.3663171231747}, "Throttle Position": {"unit": "%", "value": 14.251748263835907}, "Engine Load": {"unit": "%", "value": 11.216176955466182}, "GPS VDOP": {"unit": "precision", "value": 1.6465726286172866}, "GPS HDOP": {"unit": "precision", "value": 1.0000000298023224}, "GPS Accuracy": {"unit": "%", "value": 6.846613526344299}, "GPS PDOP": {"unit": "precision", "value": 1.9000000566244124}, "Consumption": {"unit": "l/h", "value": 1.552463372086893}, "CO2": {"unit": "kg/h", "value": 3.6482889244041985}, "Intake Pressure": {"unit": "kPa", "value": 29.356589376926422}, "GPS Bearing": {"unit": "deg", "value": 253.510154163062}, "GPS Altitude": {"unit": "m", "value": 140.10024017674115}, "Speed": {"unit": "km/h", "value": 26.0}}, "id": "58d92507268d1b091fd607f0"}, "type": "Feature", "geometry": {"coordinates": [7.998183399675762, 52.34119022490586], "type": "Point"}}, {"properties": {"time": "2017-03-27T14:39:49Z", "phenomenons": {"GPS Speed": {"unit": "km/h", "value": 33.956338118800886}, "Calculated MAF": {"unit": "g/s", "value": 7.023311384969267}, "GPS Accuracy": {"unit": "%", "value": 6.0}, "Rpm": {"unit": "u/min", "value": 2000.409839630127}, "Throttle Position": {"unit": "%", "value": 14.759183645248413}, "Engine Load": {"unit": "%", "value": 15.545531729190316}, "GPS VDOP": {"unit": "precision", "value": 0.9000000268220901}, "GPS HDOP": {"unit": "precision", "value": 1.0543564677238466}, "Intake Temperature": {"unit": "c", "value": 47.00000140070915}, "GPS PDOP": {"unit": "precision", "value": 1.354356476664543}, "Speed": {"unit": "km/h", "value": 34.05159241706133}, "Intake Pressure": {"unit": "kPa", "value": 37.96008080244064}, "CO2": {"unit": "kg/h", "value": 5.425486400661097}, "GPS Altitude": {"unit": "m", "value": 139.80248249253216}, "GPS Bearing": {"unit": "deg", "value": 253.40677910120212}, "Consumption": {"unit": "l/h", "value": 2.3087176173025945}}, "id": "58d92507268d1b091fd607f1"}, "type": "Feature", "geometry": {"coordinates": [7.997612642285746, 52.3410768141551], "type": "Point"}}, {"properties": {"time": "2017-03-27T14:39:54Z", "phenomenons": {"GPS Speed": {"unit": "km/h", "value": 34.40520623382122}, "GPS Accuracy": {"unit": "%", "value": 6.0}, "Rpm": {"unit": "u/min", "value": 899.2546649575233}, "Throttle Position": {"unit": "%", "value": 12.833560705184937}, "Engine Load": {"unit": "%", "value": 26.65310782392951}, "GPS VDOP": {"unit": "precision", "value": 1.4999999552965164}, "GPS Bearing": {"unit": "deg", "value": 249.54829685016466}, "GPS HDOP": {"unit": "precision", "value": 0.9999999701976776}, "Intake Temperature": {"unit": "c", "value": 48.000001430511475}, "GPS PDOP": {"unit": "precision", "value": 1.7999999463558196}, "Speed": {"unit": "km/h", "value": 33.99454942345619}, "CO2": {"unit": "kg/h", "value": 2.488773442619466}, "Intake Pressure": {"unit": "kPa", "value": 38.85657486319542}, "GPS Altitude": {"unit": "m", "value": 138.23763984432577}, "Calculated MAF": {"unit": "g/s", "value": 3.2217260469086386}, "Consumption": {"unit": "l/h", "value": 1.059052528774241}}, "id": "58d92507268d1b091fd607f2"}, "type": "Feature", "geometry": {"coordinates": [7.996953115859743, 52.34093434164558], "type": "Point"}}, {"properties": {"time": "2017-03-27T14:39:59Z", "phenomenons": {"GPS Speed": {"unit": "km/h", "value": 16.105757110170316}, "GPS Accuracy": {"unit": "%", "value": 8.0}, "Rpm": {"unit": "u/min", "value": 871.8677462935448}, "Throttle Position": {"unit": "%", "value": 12.0}, "Engine Load": {"unit": "%", "value": 24.496374709549173}, "GPS VDOP": {"unit": "precision", "value": 0.8999999999999999}, "GPS Bearing": {"unit": "deg", "value": 291.16076258084286}, "GPS HDOP": {"unit": "precision", "value": 1.0424725830554962}, "Intake Temperature": {"unit": "c", "value": 47.99999928474426}, "GPS PDOP": {"unit": "precision", "value": 1.3424725830554962}, "Consumption": {"unit": "l/h", "value": 0.9591758870482834}, "CO2": {"unit": "kg/h", "value": 2.254063334563466}, "Intake Pressure": {"unit": "kPa", "value": 36.29755327105522}, "Calculated MAF": {"unit": "g/s", "value": 2.9178929797247988}, "GPS Altitude": {"unit": "m", "value": 136.6143749104529}, "Speed": {"unit": "km/h", "value": 15.069948133081198}}, "id": "58d92507268d1b091fd607f3"}, "type": "Feature", "geometry": {"coordinates": [7.996515599393946, 52.34088838133313], "type": "Point"}}, {"properties": {"time": "2017-03-27T14:40:04Z", "phenomenons": {"GPS Speed": {"unit": "km/h", "value": 19.403397257971392}, "GPS Accuracy": {"unit": "%", "value": 6.0}, "Rpm": {"unit": "u/min", "value": 1324.2650704085827}, "Throttle Position": {"unit": "%", "value": 14.000000208616257}, "Engine Load": {"unit": "%", "value": 16.86274484530383}, "GPS VDOP": {"unit": "precision", "value": 1.41115460395813}, "GPS Bearing": {"unit": "deg", "value": 332.78905349458364}, "GPS HDOP": {"unit": "precision", "value": 1.3277886509895325}, "Intake Temperature": {"unit": "c", "value": 48.0}, "GPS PDOP": {"unit": "precision", "value": 1.9472602784633637}, "Speed": {"unit": "km/h", "value": 19.545081973075867}, "CO2": {"unit": "kg/h", "value": 3.746687304682386}, "Intake Pressure": {"unit": "kPa", "value": 39.72229881584644}, "GPS Altitude": {"unit": "m", "value": 134.03889994360532}, "Calculated MAF": {"unit": "g/s", "value": 4.850100002036543}, "Consumption": {"unit": "l/h", "value": 1.5943350232691005}}, "id": "58d92507268d1b091fd607f4"}, "type": "Feature", "geometry": {"coordinates": [7.9963621817209996, 52.341056388646564], "type": "Point"}}, {"properties": {"time": "2017-03-27T14:40:09Z", "phenomenons": {"GPS Speed": {"unit": "km/h", "value": 19.369739646227174}, "GPS Accuracy": {"unit": "%", "value": 7.207859575748444}, "Rpm": {"unit": "u/min", "value": 1311.9753087759018}, "Throttle Position": {"unit": "%", "value": 17.77724577486515}, "Engine Load": {"unit": "%", "value": 30.971932225171827}, "GPS VDOP": {"unit": "precision", "value": 1.5434156835079194}, "GPS Bearing": {"unit": "deg", "value": 340.48037138130167}, "GPS HDOP": {"unit": "precision", "value": 1.086831307411194}, "Intake Temperature": {"unit": "c", "value": 48.0}, "GPS PDOP": {"unit": "precision", "value": 1.8868313312530518}, "Speed": {"unit": "km/h", "value": 19.52602681517601}, "CO2": {"unit": "kg/h", "value": 6.516601803660921}, "Intake Pressure": {"unit": "kPa", "value": 69.73605442047119}, "GPS Altitude": {"unit": "m", "value": 132.53668706878383}, "Calculated MAF": {"unit": "g/s", "value": 8.435764143356096}, "Consumption": {"unit": "l/h", "value": 2.77302204411103}}, "id": "58d92507268d1b091fd607f5"}, "type": "Feature", "geometry": {"coordinates": [7.996304794922746, 52.34126264718869], "type": "Point"}}, {"properties": {"time": "2017-03-27T14:40:14Z", "phenomenons": {"GPS Speed": {"unit": "km/h", "value": 20.358877209775983}, "Calculated MAF": {"unit": "g/s", "value": 8.715089945373439}, "GPS Accuracy": {"unit": "%", "value": 8.0}, "Rpm": {"unit": "u/min", "value": 1459.0487806200981}, "Throttle Position": {"unit": "%", "value": 17.0}, "Engine Load": {"unit": "%", "value": 28.014856995220157}, "GPS VDOP": {"unit": "precision", "value": 1.5}, "GPS HDOP": {"unit": "precision", "value": 1.0}, "Intake Temperature": {"unit": "c", "value": 47.0}, "GPS PDOP": {"unit": "precision", "value": 1.8}, "Speed": {"unit": "km/h", "value": 21.923684865236282}, "CO2": {"unit": "kg/h", "value": 6.732380124901548}, "Intake Pressure": {"unit": "kPa", "value": 64.58122020959854}, "GPS Altitude": {"unit": "m", "value": 132.70370447841313}, "GPS Bearing": {"unit": "deg", "value": 215.03029630292326}, "Consumption": {"unit": "l/h", "value": 2.864842606341084}}, "id": "58d92507268d1b091fd607f6"}, "type": "Feature", "geometry": {"coordinates": [7.996195143276118, 52.3414837872847], "type": "Point"}}, {"properties": {"time": "2017-03-27T14:40:19Z", "phenomenons": {"GPS Speed": {"unit": "km/h", "value": 19.245243718945062}, "GPS Accuracy": {"unit": "%", "value": 8.0}, "Rpm": {"unit": "u/min", "value": 1307.3287857174873}, "Throttle Position": {"unit": "%", "value": 16.0}, "Engine Load": {"unit": "%", "value": 25.824038182957594}, "GPS VDOP": {"unit": "precision", "value": 0.8416000008583069}, "GPS HDOP": {"unit": "precision", "value": 1.0832000017166137}, "GPS Altitude": {"unit": "m", "value": 132.5111184120143}, "Intake Temperature": {"unit": "c", "value": 47.0}, "GPS PDOP": {"unit": "precision", "value": 1.383200001716614}, "Consumption": {"unit": "l/h", "value": 2.419894003891497}, "CO2": {"unit": "kg/h", "value": 5.686750909145019}, "Intake Pressure": {"unit": "kPa", "value": 60.88170564174652}, "GPS Bearing": {"unit": "deg", "value": 151.82343203021117}, "Calculated MAF": {"unit": "g/s", "value": 7.361519217671591}, "Speed": {"unit": "km/h", "value": 19.39319670200348}}, "id": "58d92507268d1b091fd607f7"}, "type": "Feature", "geometry": {"coordinates": [7.996072147218129, 52.34171472804101], "type": "Point"}}, {"properties": {"time": "2017-03-27T14:40:24Z", "phenomenons": {"GPS Speed": {"unit": "km/h", "value": 19.500728029659058}, "GPS Accuracy": {"unit": "%", "value": 8.0}, "Rpm": {"unit": "u/min", "value": 1231.1479987949133}, "Throttle Position": {"unit": "%", "value": 17.0}, "Engine Load": {"unit": "%", "value": 32.33895210418916}, "GPS VDOP": {"unit": "precision", "value": 0.9000000268220902}, "GPS Bearing": {"unit": "deg", "value": 330.3473260866758}, "GPS HDOP": {"unit": "precision", "value": 1.0441468566656114}, "Intake Temperature": {"unit": "c", "value": 47.0}, "GPS PDOP": {"unit": "precision", "value": 1.4000000417232512}, "Speed": {"unit": "km/h", "value": 18.145355731248856}, "CO2": {"unit": "kg/h", "value": 6.3337057106912065}, "Intake Pressure": {"unit": "kPa", "value": 72.0037385225296}, "Calculated MAF": {"unit": "g/s", "value": 8.199004502439095}, "GPS Altitude": {"unit": "m", "value": 131.75313631472216}, "Consumption": {"unit": "l/h", "value": 2.6951939194430663}}, "id": "58d92507268d1b091fd607f8"}, "type": "Feature", "geometry": {"coordinates": [7.996072639103279, 52.34193164848725], "type": "Point"}}, {"properties": {"time": "2017-03-27T14:40:29Z", "phenomenons": {"GPS Speed": {"unit": "km/h", "value": 18.859299553559254}, "GPS Accuracy": {"unit": "%", "value": 6.000000178813934}, "Rpm": {"unit": "u/min", "value": 1338.129161119461}, "Throttle Position": {"unit": "%", "value": 14.936263844370842}, "Engine Load": {"unit": "%", "value": 22.74509879187042}, "GPS VDOP": {"unit": "precision", "value": 1.5386706948280335}, "GPS Bearing": {"unit": "deg", "value": 346.5695432138955}, "GPS HDOP": {"unit": "precision", "value": 1.0773413896560669}, "Intake Temperature": {"unit": "c", "value": 46.999999299645424}, "GPS PDOP": {"unit": "precision", "value": 1.877341389656067}, "Speed": {"unit": "km/h", "value": 19.999999403953552}, "CO2": {"unit": "kg/h", "value": 5.021004208994566}, "Intake Pressure": {"unit": "kPa", "value": 52.51700836420059}, "GPS Altitude": {"unit": "m", "value": 132.6957303004466}, "Calculated MAF": {"unit": "g/s", "value": 6.499707753522929}, "Consumption": {"unit": "l/h", "value": 2.1365975357423683}}, "id": "58d92507268d1b091fd607f9"}, "type": "Feature", "geometry": {"coordinates": [7.995937653216211, 52.34217391771358], "type": "Point"}}, {"properties": {"time": "2017-03-27T14:40:34Z", "phenomenons": {"GPS Speed": {"unit": "km/h", "value": 12.510253581380596}, "Intake Temperature": {"unit": "c", "value": 47.0}, "Rpm": {"unit": "u/min", "value": 1028.3141481354833}, "Throttle Position": {"unit": "%", "value": 13.862371921539307}, "Engine Load": {"unit": "%", "value": 34.420169011284315}, "GPS VDOP": {"unit": "precision", "value": 1.2}, "GPS Bearing": {"unit": "deg", "value": 343.3177711308999}, "GPS HDOP": {"unit": "precision", "value": 0.9000000000000001}, "GPS Accuracy": {"unit": "%", "value": 7.234886050224304}, "GPS PDOP": {"unit": "precision", "value": 1.5}, "Consumption": {"unit": "l/h", "value": 1.4237849919152288}, "Intake Pressure": {"unit": "kPa", "value": 45.540090680122375}, "CO2": {"unit": "kg/h", "value": 3.345894731000788}, "Calculated MAF": {"unit": "g/s", "value": 4.331272594155452}, "GPS Altitude": {"unit": "m", "value": 132.67574363182575}, "Speed": {"unit": "km/h", "value": 13.150760918855667}}, "id": "58d92507268d1b091fd607fa"}, "type": "Feature", "geometry": {"coordinates": [7.9958747257979645, 52.342360636691026], "type": "Point"}}, {"properties": {"time": "2017-03-27T14:40:39Z", "phenomenons": {"GPS Speed": {"unit": "km/h", "value": 12.915749469887373}, "Calculated MAF": {"unit": "g/s", "value": 10.771342381997815}, "Intake Temperature": {"unit": "c", "value": 46.999999299645424}, "Rpm": {"unit": "u/min", "value": 1287.9373365938663}, "Throttle Position": {"unit": "%", "value": 23.128672778606415}, "Engine Load": {"unit": "%", "value": 42.15745620932648}, "GPS VDOP": {"unit": "precision", "value": 1.2}, "GPS HDOP": {"unit": "precision", "value": 0.8999999999999999}, "GPS Accuracy": {"unit": "%", "value": 7.999999761581421}, "GPS PDOP": {"unit": "precision", "value": 1.5}, "Speed": {"unit": "km/h", "value": 19.65722954273224}, "CO2": {"unit": "kg/h", "value": 8.320828795297587}, "Intake Pressure": {"unit": "kPa", "value": 90.4230769276619}, "GPS Altitude": {"unit": "m", "value": 133.17940059799673}, "GPS Bearing": {"unit": "deg", "value": 139.8400307160602}, "Consumption": {"unit": "l/h", "value": 3.5407782107649304}}, "id": "58d92507268d1b091fd607fb"}, "type": "Feature", "geometry": {"coordinates": [7.9958020556034315, 52.34253759494864], "type": "Point"}}, {"properties": {"time": "2017-03-27T14:40:44Z", "phenomenons": {"GPS Speed": {"unit": "km/h", "value": 24.713031814911915}, "Calculated MAF": {"unit": "g/s", "value": 7.913485482843011}, "GPS Accuracy": {"unit": "%", "value": 6.728529095649719}, "Rpm": {"unit": "u/min", "value": 1663.6095616221428}, "Throttle Position": {"unit": "%", "value": 15.71879106760025}, "Engine Load": {"unit": "%", "value": 21.941202281145593}, "GPS VDOP": {"unit": "precision", "value": 1.600000047683716}, "GPS HDOP": {"unit": "precision", "value": 1.2000000357627867}, "Intake Temperature": {"unit": "c", "value": 47.0}, "GPS PDOP": {"unit": "precision", "value": 2.0000000596046448}, "Consumption": {"unit": "l/h", "value": 2.6013375097689666}, "CO2": {"unit": "kg/h", "value": 6.1131431479570715}, "Intake Pressure": {"unit": "kPa", "value": 51.43048109859228}, "GPS Bearing": {"unit": "deg", "value": 356.28198990137753}, "GPS Altitude": {"unit": "m", "value": 133.4728645187083}, "Speed": {"unit": "km/h", "value": 24.99999925494194}}, "id": "58d92507268d1b091fd607fc"}, "type": "Feature", "geometry": {"coordinates": [7.995787057597617, 52.342831168531205], "type": "Point"}}, {"properties": {"time": "2017-03-27T14:40:49Z", "phenomenons": {"GPS Speed": {"unit": "km/h", "value": 24.935080377279576}, "Calculated MAF": {"unit": "g/s", "value": 7.489016257214396}, "GPS Accuracy": {"unit": "%", "value": 6.000000178813934}, "Rpm": {"unit": "u/min", "value": 1582.1599496658891}, "Throttle Position": {"unit": "%", "value": 15.481378853321075}, "Engine Load": {"unit": "%", "value": 21.746536092636234}, "GPS VDOP": {"unit": "precision", "value": 1.3828920155763627}, "GPS HDOP": {"unit": "precision", "value": 0.9414460003376007}, "Intake Temperature": {"unit": "c", "value": 47.0}, "GPS PDOP": {"unit": "precision", "value": 1.682892006635666}, "Speed": {"unit": "km/h", "value": 24.000000715255737}, "Intake Pressure": {"unit": "kPa", "value": 51.17744159698486}, "CO2": {"unit": "kg/h", "value": 5.785241979275331}, "GPS Bearing": {"unit": "deg", "value": 345.865881746573}, "GPS Altitude": {"unit": "m", "value": 134.6753113206704}, "Consumption": {"unit": "l/h", "value": 2.4618050975639707}}, "id": "58d92507268d1b091fd607fd"}, "type": "Feature", "geometry": {"coordinates": [7.995754461803876, 52.34315181792048], "type": "Point"}}], "type": "FeatureCollection"}